{"name":"Adobe Cyrillic 1","glyphs":[{"codepoints":[1024]},{"codepoints":[1025]},{"codepoints":[1026]},{"codepoints":[1027]},{"codepoints":[1028]},{"codepoints":[1029]},{"codepoints":[1030]},{"codepoints":[1031]},{"codepoints":[1032]},{"codepoints":[1033]},{"codepoints":[1034]},{"codepoints":[1035]},{"codepoints":[1036]},{"codepoints":[1037]},{"codepoints":[1038]},{"codepoints":[1039]},{"codepoints":[1040]},{"codepoints":[1041]},{"codepoints":[1042]},{"codepoints":[1043]},{"codepoints":[1044]},{"codepoints":[1045]},{"codepoints":[1046]},{"codepoints":[1047]},{"codepoints":[1048]},{"codepoints":[1049]},{"codepoints":[1050]},{"codepoints":[1051]},{"codepoints":[1052]},{"codepoints":[1053]},{"codepoints":[1054]},{"codepoints":[1055]},{"codepoints":[1056]},{"codepoints":[1057]},{"codepoints":[1058]},{"codepoints":[1059]},{"codepoints":[1060]},{"codepoints":[1061]},{"codepoints":[1062]},{"codepoints":[1063]},{"codepoints":[1064]},{"codepoints":[1065]},{"codepoints":[1066]},{"codepoints":[1067]},{"codepoints":[1068]},{"codepoints":[1069]},{"codepoints":[1070]},{"codepoints":[1071]},{"codepoints":[1072]},{"codepoints":[1073]},{"codepoints":[1074]},{"codepoints":[1075]},{"codepoints":[1076]},{"codepoints":[1077]},{"codepoints":[1078]},{"codepoints":[1079]},{"codepoints":[1080]},{"codepoints":[1081]},{"codepoints":[1082]},{"codepoints":[1083]},{"codepoints":[1084]},{"codepoints":[1085]},{"codepoints":[1086]},{"codepoints":[1087]},{"codepoints":[1088]},{"codepoints":[1089]},{"codepoints":[1090]},{"codepoints":[1091]},{"codepoints":[1092]},{"codepoints":[1093]},{"codepoints":[1094]},{"codepoints":[1095]},{"codepoints":[1096]},{"codepoints":[1097]},{"codepoints":[1098]},{"codepoints":[1099]},{"codepoints":[1100]},{"codepoints":[1101]},{"codepoints":[1102]},{"codepoints":[1103]},{"codepoints":[1104]},{"codepoints":[1105]},{"codepoints":[1106]},{"codepoints":[1107]},{"codepoints":[1108]},{"codepoints":[1109]},{"codepoints":[1110]},{"codepoints":[1111]},{"codepoints":[1112]},{"codepoints":[1113]},{"codepoints":[1114]},{"codepoints":[1115]},{"codepoints":[1116]},{"codepoints":[1117]},{"codepoints":[1118]},{"codepoints":[1119]},{"codepoints":[1122]},{"codepoints":[1123]},{"codepoints":[1138]},{"codepoints":[1139]},{"codepoints":[1140]},{"codepoints":[1141]},{"codepoints":[1168]},{"codepoints":[1169]},{"codepoints":[8372]},{"codepoints":[8381]},{"codepoints":[8470]}]}